{ "nodes": [{"Name": "FOXC1", "d": 1.4992299853119007, "color": "rgb(102, 255, 51)", "type": "square", "label": "FOXC1", "x": 0.3091526479541076, "y": -0.7192529951624547, "size": 10, "id": "FOXC1"}, {"Name": "CDC45", "d": 0.5490035868231182, "color": "rgb(153, 255, 51)", "type": "square", "label": "CDC45", "x": 0.46293572315619436, "y": -0.15027135406208209, "size": 10, "id": "CDC45"}, {"Name": "FOXC2", "d": 0.6483090843780925, "color": "rgb(153, 255, 51)", "type": "square", "label": "FOXC2", "x": 0.37579849071903865, "y": -0.824370510130204, "size": 10, "id": "FOXC2"}, {"Name": "DLX5", "d": 0.932662414510655, "color": "rgb(153, 255, 51)", "type": "square", "label": "DLX5", "x": 0.2309264600810535, "y": -0.7847663439180027, "size": 10, "id": "DLX5"}, {"Name": "PLK1", "d": 1.0681247413525985, "color": "rgb(102, 255, 51)", "type": "square", "label": "PLK1", "x": 0.37674390692264936, "y": -0.2620971081372932, "size": 10, "id": "PLK1"}, {"Name": "SATB2", "d": 0.19127871073226377, "color": "rgb(204, 255, 51)", "type": "square", "label": "SATB2", "x": 0.34551444722075114, "y": -0.5881006074684725, "size": 10, "id": "SATB2"}, {"Name": "MYC", "d": 0.9585067960130981, "color": "rgb(153, 255, 51)", "type": "square", "label": "MYC", "x": -0.0013419514247719135, "y": -0.020672414447093883, "size": 10, "id": "MYC"}, {"Name": "PKP1", "d": 1.1973130482704488, "color": "rgb(102, 255, 51)", "type": "square", "label": "PKP1", "x": -0.04260947588164862, "y": -0.27460852098758654, "size": 10, "id": "PKP1"}, {"Name": "DSG1", "d": 0.42743028503806246, "color": "rgb(204, 255, 51)", "type": "square", "label": "DSG1", "x": 0.05540748556565259, "y": -0.19697280214776752, "size": 10, "id": "DSG1"}, {"Name": "MCM10", "d": 0.9630675879090427, "color": "rgb(153, 255, 51)", "type": "square", "label": "MCM10", "x": 0.3371106452559863, "y": -0.08532648391233218, "size": 10, "id": "MCM10"}, {"Name": "CDKN2A", "d": 1.2217597919328285, "color": "rgb(102, 255, 51)", "type": "square", "label": "CDKN2A", "x": 0.24937648985186872, "y": -0.11969871859448417, "size": 10, "id": "CDKN2A"}, {"Name": "AR", "d": -1.5298609654151365, "color": "rgb(255, 153, 51)", "type": "circle", "label": "AR", "x": -0.07162589981329545, "y": -0.1522073623096111, "size": 10, "id": "AR"}, {"Name": "ERBB2", "d": -0.6901227586337506, "color": "rgb(255, 255, 0)", "type": "circle", "label": "ERBB2", "x": -0.38039568938053875, "y": 0.28813480459538193, "size": 10, "id": "ERBB2"}, {"Name": "FOS", "d": -0.5737783924069446, "color": "rgb(255, 255, 0)", "type": "circle", "label": "FOS", "x": 0.0016308572685319665, "y": -0.1994058606328219, "size": 10, "id": "FOS"}, {"Name": "ESR1", "d": -1.3779731928173615, "color": "rgb(255, 204, 0)", "type": "circle", "label": "ESR1", "x": -0.23849330336284816, "y": 0.06735885242734296, "size": 10, "id": "ESR1"}, {"Name": "CST1", "d": -0.5763681290520244, "color": "rgb(255, 255, 0)", "type": "circle", "label": "CST1", "x": -0.20640244602803304, "y": -0.8197191745949235, "size": 10, "id": "CST1"}, {"Name": "MUC1", "d": -1.5714490008633364, "color": "rgb(255, 153, 51)", "type": "circle", "label": "MUC1", "x": -0.4510534697117229, "y": 0.3072721035875097, "size": 10, "id": "MUC1"}, {"Name": "APOD", "d": -0.9948569636265705, "color": "rgb(255, 255, 0)", "type": "circle", "label": "APOD", "x": 0.02216497865477046, "y": 0.12524465204587706, "size": 10, "id": "APOD"}, {"Name": "GSTM2", "d": -0.9385180878931518, "color": "rgb(255, 255, 0)", "type": "circle", "label": "GSTM2", "x": -0.9331832945886054, "y": -0.10553119730098923, "size": 10, "id": "GSTM2"}, {"Name": "GLCE", "d": -0.299921930832573, "color": "rgb(204, 255, 51)", "type": "circle", "label": "GLCE", "x": -0.27064852424943364, "y": 0.20809483688525215, "size": 10, "id": "GLCE"}, {"Name": "GRB7", "d": -0.326172479363128, "color": "rgb(204, 255, 51)", "type": "circle", "label": "GRB7", "x": -0.03744139596761113, "y": 0.4156608555097569, "size": 10, "id": "GRB7"}, {"Name": "DPPA4", "d": 0.3019505514296071, "color": "rgb(204, 255, 51)", "type": "circle", "label": "DPPA4", "x": 0.2295674395351213, "y": 0.053190499121488974, "size": 10, "id": "DPPA4"}, {"Name": "VAV3", "d": -1.4242773238287427, "color": "rgb(255, 204, 0)", "type": "circle", "label": "VAV3", "x": -0.4555237781032895, "y": 0.10260818874918201, "size": 10, "id": "VAV3"}, {"Name": "TENM3", "d": 0.3296320676260789, "color": "rgb(204, 255, 51)", "type": "circle", "label": "TENM3", "x": 0.4311852933607442, "y": 0.1955368103982092, "size": 10, "id": "TENM3"}, {"Name": "CCND1", "d": -0.7960039800373049, "color": "rgb(255, 255, 0)", "type": "circle", "label": "CCND1", "x": 0.07811583318648346, "y": -0.04786770901969826, "size": 10, "id": "CCND1"}, {"Name": "BORCS6", "d": -0.6662272784440519, "color": "rgb(255, 255, 0)", "type": "circle", "label": "BORCS6", "x": 0.9650836126278332, "y": -0.4054851038259028, "size": 10, "id": "BORCS6"}, {"Name": "EEF1A2", "d": -0.9498963208658164, "color": "rgb(255, 255, 0)", "type": "circle", "label": "EEF1A2", "x": -0.46293509654581694, "y": 0.7528511035613751, "size": 10, "id": "EEF1A2"}, {"Name": "PGR", "d": -1.1174160224250147, "color": "rgb(255, 204, 0)", "type": "circle", "label": "PGR", "x": -0.2631074445998951, "y": -0.03999753069008218, "size": 10, "id": "PGR"}, {"Name": "HSPB8", "d": -0.5867275629402116, "color": "rgb(255, 255, 0)", "type": "circle", "label": "HSPB8", "x": -0.5173315632161665, "y": 0.5982062103868632, "size": 10, "id": "HSPB8"}, {"Name": "GSTM3", "d": -1.215476796950838, "color": "rgb(255, 204, 0)", "type": "circle", "label": "GSTM3", "x": -0.6724666287993616, "y": -0.069379597587757, "size": 10, "id": "GSTM3"}, {"Name": "ERBB4", "d": -1.4845628804204951, "color": "rgb(255, 204, 0)", "type": "circle", "label": "ERBB4", "x": -0.5996323006555287, "y": 0.3722098026647647, "size": 10, "id": "ERBB4"}, {"Name": "GKN1", "d": 0.4371631306547007, "color": "rgb(204, 255, 51)", "type": "circle", "label": "GKN1", "x": -0.2665602335337991, "y": -0.9909814920731571, "size": 10, "id": "GKN1"}, {"Name": "PIGR", "d": -0.4368304301675607, "color": "rgb(204, 255, 51)", "type": "circle", "label": "PIGR", "x": -0.140646763963681, "y": -0.8579436490155875, "size": 10, "id": "PIGR"}, {"Name": "ARMT1", "d": -1.3329742256541919, "color": "rgb(255, 204, 0)", "type": "circle", "label": "ARMT1", "x": -0.40639453090890126, "y": 0.5932210946768405, "size": 10, "id": "ARMT1"}, {"Name": "IFT74", "d": -0.960124619841768, "color": "rgb(255, 255, 0)", "type": "circle", "label": "IFT74", "x": 0.9999999999999999, "y": -0.30241848408130934, "size": 10, "id": "IFT74"}, {"Name": "MYO6", "d": -0.9519170520490401, "color": "rgb(255, 255, 0)", "type": "circle", "label": "MYO6", "x": -0.41299168328764957, "y": -0.02392047049528372, "size": 10, "id": "MYO6"}, {"Name": "HSPB1", "d": -0.6973103773453364, "color": "rgb(255, 255, 0)", "type": "circle", "label": "HSPB1", "x": -0.33741342068200697, "y": 0.3345950879138429, "size": 10, "id": "HSPB1"}, {"Name": "FOXA1", "d": -1.9327537401094355, "color": "rgb(255, 153, 51)", "type": "circle", "label": "FOXA1", "x": 0.12167404866990976, "y": -0.5193387359605517, "size": 10, "id": "FOXA1"}, {"Name": "ODF2", "d": -0.44366339518061004, "color": "rgb(204, 255, 51)", "type": "circle", "label": "ODF2", "x": 0.7577684625237302, "y": -0.2077967744736723, "size": 10, "id": "ODF2"}, {"Name": "PRKCD", "d": -0.775089721463402, "color": "rgb(255, 255, 0)", "type": "circle", "label": "PRKCD", "x": -0.3139609373774705, "y": 0.4620294738127696, "size": 10, "id": "PRKCD"}, {"Name": "PAK1", "d": 0.0004451079305554386, "color": "rgb(204, 255, 51)", "type": "circle", "label": "PAK1", "x": -0.3680108582977399, "y": 0.22410439623559103, "size": 10, "id": "PAK1"}, {"Name": "ASB4", "d": 0.051476319948890126, "color": "rgb(204, 255, 51)", "type": "circle", "label": "ASB4", "x": -0.5780455950727923, "y": 0.5159604100830038, "size": 10, "id": "ASB4"}, {"Name": "PTPRG", "d": 0.005625522446436588, "color": "rgb(204, 255, 51)", "type": "circle", "label": "PTPRG", "x": 0.5667094697560301, "y": 0.7809487156777952, "size": 10, "id": "PTPRG"}, {"Name": "TRIM36", "d": -0.471915129029848, "color": "rgb(204, 255, 51)", "type": "circle", "label": "TRIM36", "x": 0.37624823164861715, "y": 0.3489385731145801, "size": 10, "id": "TRIM36"}, {"Name": "NIN", "d": -0.28635225956523014, "color": "rgb(204, 255, 51)", "type": "circle", "label": "NIN", "x": 0.7348345947242423, "y": -0.2930459492099449, "size": 10, "id": "NIN"}, {"Name": "REPS2", "d": -0.9135752350645462, "color": "rgb(255, 255, 0)", "type": "circle", "label": "REPS2", "x": -0.33497507256972736, "y": -0.22556619109203915, "size": 10, "id": "REPS2"}, {"Name": "NFIX", "d": 0.19699253407973633, "color": "rgb(204, 255, 51)", "type": "circle", "label": "NFIX", "x": 0.18145435254045184, "y": -0.4963444078468879, "size": 10, "id": "NFIX"}, {"Name": "XBP1", "d": -1.711027700629098, "color": "rgb(255, 153, 51)", "type": "circle", "label": "XBP1", "x": -0.15213708840447476, "y": -0.09884008693338237, "size": 10, "id": "XBP1"}, {"Name": "ZBTB16", "d": -0.6054978548098686, "color": "rgb(255, 255, 0)", "type": "circle", "label": "ZBTB16", "x": -0.03021938007974851, "y": 0.2786898390885494, "size": 10, "id": "ZBTB16"}, {"Name": "SCGB2A2", "d": -1.1643520059629027, "color": "rgb(255, 204, 0)", "type": "circle", "label": "SCGB2A2", "x": 0.5616775430454947, "y": 0.5287387461947762, "size": 10, "id": "SCGB2A2"}, {"Name": "KRT18", "d": -1.5534087004394863, "color": "rgb(255, 153, 51)", "type": "circle", "label": "KRT18", "x": -0.46162779473995735, "y": 0.18051377825859713, "size": 10, "id": "KRT18"}, {"Name": "IL32", "d": 0.5004802494273766, "color": "rgb(153, 255, 51)", "type": "circle", "label": "IL32", "x": -0.12123479113945854, "y": 0.5199683891798808, "size": 10, "id": "IL32"}, {"Name": "SPICE1", "d": -0.12949824785262248, "color": "rgb(204, 255, 51)", "type": "circle", "label": "SPICE1", "x": 0.711468781550998, "y": 0.1639192257225534, "size": 10, "id": "SPICE1"}, {"Name": "FGB", "d": -0.2761672353082962, "color": "rgb(204, 255, 51)", "type": "circle", "label": "FGB", "x": -0.3032187983978493, "y": 0.5424968519477814, "size": 10, "id": "FGB"}, {"Name": "FKBP5", "d": 0.2737097553858581, "color": "rgb(204, 255, 51)", "type": "circle", "label": "FKBP5", "x": -0.26475632380723424, "y": -0.1341305809307375, "size": 10, "id": "FKBP5"}, {"Name": "DDX31", "d": -0.3402107087897041, "color": "rgb(204, 255, 51)", "type": "circle", "label": "DDX31", "x": -0.026830645739334084, "y": -0.5868346763387579, "size": 10, "id": "DDX31"}, {"Name": "MX1", "d": -0.012736271057619396, "color": "rgb(204, 255, 51)", "type": "circle", "label": "MX1", "x": 0.1775218233383922, "y": 0.5974657217270214, "size": 10, "id": "MX1"}, {"Name": "CLU", "d": -0.6149509109641653, "color": "rgb(255, 255, 0)", "type": "circle", "label": "CLU", "x": 0.2078313382043346, "y": -0.17557155109694716, "size": 10, "id": "CLU"}, {"Name": "PTPRT", "d": -1.0140419188072594, "color": "rgb(255, 204, 0)", "type": "circle", "label": "PTPRT", "x": -0.6708228740160882, "y": 0.3355791626963027, "size": 10, "id": "PTPRT"}, {"Name": "DIAPH3", "d": 0.31932507551668227, "color": "rgb(204, 255, 51)", "type": "circle", "label": "DIAPH3", "x": 0.8351870915840159, "y": -0.06639562938156511, "size": 10, "id": "DIAPH3"}, {"Name": "MPHOSPH9", "d": -0.09504297617223044, "color": "rgb(204, 255, 51)", "type": "circle", "label": "MPHOSPH9", "x": 0.8830032806785857, "y": 0.009338000320960204, "size": 10, "id": "MPHOSPH9"}, {"Name": "IRS1", "d": -0.9277082462413369, "color": "rgb(255, 255, 0)", "type": "circle", "label": "IRS1", "x": -0.2618097000266131, "y": 0.32077828902370953, "size": 10, "id": "IRS1"}, {"Name": "PSD3", "d": -0.6535772194586271, "color": "rgb(255, 255, 0)", "type": "circle", "label": "PSD3", "x": 0.3771277295860063, "y": 0.803731387132739, "size": 10, "id": "PSD3"}, {"Name": "GSTM1", "d": -0.8768593613794555, "color": "rgb(255, 255, 0)", "type": "circle", "label": "GSTM1", "x": -0.9073723048385064, "y": -0.18252578888091703, "size": 10, "id": "GSTM1"}], "edges": [{"id": 45, "color": "rgb(0,0,0)", "source": "FOXC1", "target": "SATB2"}, {"id": 65, "color": "rgb(0,0,0)", "source": "FOXC1", "target": "FOXC2"}, {"id": 72, "color": "rgb(0,0,0)", "source": "FOXC1", "target": "DLX5"}, {"id": 95, "color": "rgb(0,0,0)", "source": "FOXC1", "target": "NFIX"}, {"id": 51, "color": "rgb(0,0,0)", "source": "CDC45", "target": "CDKN2A"}, {"id": 63, "color": "rgb(0,0,0)", "source": "CDC45", "target": "MCM10"}, {"id": 44, "color": "rgb(0,0,0)", "source": "FOXC2", "target": "SATB2"}, {"id": 64, "color": "rgb(0,0,0)", "source": "FOXC2", "target": "DLX5"}, {"id": 71, "color": "rgb(0,0,0)", "source": "DLX5", "target": "FOXA1"}, {"id": 42, "color": "rgb(0,0,0)", "source": "PLK1", "target": "SATB2"}, {"id": 73, "color": "rgb(0,0,0)", "source": "PLK1", "target": "CLU"}, {"id": 74, "color": "rgb(0,0,0)", "source": "PLK1", "target": "MYC"}, {"id": 75, "color": "rgb(0,0,0)", "source": "PLK1", "target": "DSG1"}, {"id": 76, "color": "rgb(0,0,0)", "source": "PLK1", "target": "NIN"}, {"id": 77, "color": "rgb(0,0,0)", "source": "PLK1", "target": "ODF2"}, {"id": 43, "color": "rgb(0,0,0)", "source": "SATB2", "target": "FOXA1"}, {"id": 22, "color": "rgb(0,0,0)", "source": "MYC", "target": "ESR1"}, {"id": 49, "color": "rgb(0,0,0)", "source": "MYC", "target": "PKP1"}, {"id": 53, "color": "rgb(0,0,0)", "source": "MYC", "target": "CDKN2A"}, {"id": 85, "color": "rgb(0,0,0)", "source": "MYC", "target": "HSPB1"}, {"id": 50, "color": "rgb(0,0,0)", "source": "PKP1", "target": "DSG1"}, {"id": 24, "color": "rgb(0,0,0)", "source": "DSG1", "target": "ESR1"}, {"id": 52, "color": "rgb(0,0,0)", "source": "MCM10", "target": "CDKN2A"}, {"id": 58, "color": "rgb(0,0,0)", "source": "MCM10", "target": "CCND1"}, {"id": 54, "color": "rgb(0,0,0)", "source": "CDKN2A", "target": "CCND1"}, {"id": 0, "color": "rgb(0,0,0)", "source": "AR", "target": "ZBTB16"}, {"id": 1, "color": "rgb(0,0,0)", "source": "AR", "target": "FKBP5"}, {"id": 2, "color": "rgb(0,0,0)", "source": "AR", "target": "CCND1"}, {"id": 3, "color": "rgb(0,0,0)", "source": "AR", "target": "FOXA1"}, {"id": 4, "color": "rgb(0,0,0)", "source": "AR", "target": "REPS2"}, {"id": 5, "color": "rgb(0,0,0)", "source": "ERBB2", "target": "ESR1"}, {"id": 6, "color": "rgb(0,0,0)", "source": "ERBB2", "target": "IRS1"}, {"id": 7, "color": "rgb(0,0,0)", "source": "ERBB2", "target": "ERBB4"}, {"id": 8, "color": "rgb(0,0,0)", "source": "ERBB2", "target": "MUC1"}, {"id": 9, "color": "rgb(0,0,0)", "source": "ERBB2", "target": "GRB7"}, {"id": 10, "color": "rgb(0,0,0)", "source": "ERBB2", "target": "PAK1"}, {"id": 11, "color": "rgb(0,0,0)", "source": "ERBB2", "target": "VAV3"}, {"id": 12, "color": "rgb(0,0,0)", "source": "ERBB2", "target": "GLCE"}, {"id": 13, "color": "rgb(0,0,0)", "source": "ERBB2", "target": "PTPRT"}, {"id": 17, "color": "rgb(0,0,0)", "source": "FOS", "target": "ESR1"}, {"id": 97, "color": "rgb(0,0,0)", "source": "FOS", "target": "NFIX"}, {"id": 98, "color": "rgb(0,0,0)", "source": "FOS", "target": "XBP1"}, {"id": 104, "color": "rgb(0,0,0)", "source": "FOS", "target": "CLU"}, {"id": 14, "color": "rgb(0,0,0)", "source": "ESR1", "target": "ZBTB16"}, {"id": 15, "color": "rgb(0,0,0)", "source": "ESR1", "target": "IRS1"}, {"id": 16, "color": "rgb(0,0,0)", "source": "ESR1", "target": "KRT18"}, {"id": 18, "color": "rgb(0,0,0)", "source": "ESR1", "target": "MYO6"}, {"id": 19, "color": "rgb(0,0,0)", "source": "ESR1", "target": "PGR"}, {"id": 20, "color": "rgb(0,0,0)", "source": "ESR1", "target": "HSPB1"}, {"id": 21, "color": "rgb(0,0,0)", "source": "ESR1", "target": "GSTM3"}, {"id": 23, "color": "rgb(0,0,0)", "source": "ESR1", "target": "APOD"}, {"id": 25, "color": "rgb(0,0,0)", "source": "ESR1", "target": "FKBP5"}, {"id": 26, "color": "rgb(0,0,0)", "source": "ESR1", "target": "MUC1"}, {"id": 27, "color": "rgb(0,0,0)", "source": "ESR1", "target": "CCND1"}, {"id": 28, "color": "rgb(0,0,0)", "source": "ESR1", "target": "PAK1"}, {"id": 29, "color": "rgb(0,0,0)", "source": "ESR1", "target": "XBP1"}, {"id": 30, "color": "rgb(0,0,0)", "source": "ESR1", "target": "VAV3"}, {"id": 31, "color": "rgb(0,0,0)", "source": "ESR1", "target": "GLCE"}, {"id": 32, "color": "rgb(0,0,0)", "source": "CST1", "target": "DDX31"}, {"id": 33, "color": "rgb(0,0,0)", "source": "CST1", "target": "GKN1"}, {"id": 34, "color": "rgb(0,0,0)", "source": "MUC1", "target": "ERBB4"}, {"id": 35, "color": "rgb(0,0,0)", "source": "MUC1", "target": "PRKCD"}, {"id": 36, "color": "rgb(0,0,0)", "source": "APOD", "target": "DPPA4"}, {"id": 37, "color": "rgb(0,0,0)", "source": "GSTM2", "target": "GSTM3"}, {"id": 38, "color": "rgb(0,0,0)", "source": "GSTM2", "target": "GSTM1"}, {"id": 46, "color": "rgb(0,0,0)", "source": "GRB7", "target": "ZBTB16"}, {"id": 47, "color": "rgb(0,0,0)", "source": "GRB7", "target": "FGB"}, {"id": 48, "color": "rgb(0,0,0)", "source": "GRB7", "target": "TRIM36"}, {"id": 55, "color": "rgb(0,0,0)", "source": "DPPA4", "target": "CLU"}, {"id": 56, "color": "rgb(0,0,0)", "source": "TENM3", "target": "CLU"}, {"id": 57, "color": "rgb(0,0,0)", "source": "TENM3", "target": "SCGB2A2"}, {"id": 59, "color": "rgb(0,0,0)", "source": "BORCS6", "target": "NIN"}, {"id": 60, "color": "rgb(0,0,0)", "source": "BORCS6", "target": "IFT74"}, {"id": 61, "color": "rgb(0,0,0)", "source": "EEF1A2", "target": "HSPB8"}, {"id": 62, "color": "rgb(0,0,0)", "source": "EEF1A2", "target": "FGB"}, {"id": 66, "color": "rgb(0,0,0)", "source": "PGR", "target": "FKBP5"}, {"id": 67, "color": "rgb(0,0,0)", "source": "HSPB8", "target": "HSPB1"}, {"id": 68, "color": "rgb(0,0,0)", "source": "HSPB8", "target": "ASB4"}, {"id": 39, "color": "rgb(0,0,0)", "source": "GSTM3", "target": "GSTM1"}, {"id": 69, "color": "rgb(0,0,0)", "source": "ERBB4", "target": "PTPRT"}, {"id": 70, "color": "rgb(0,0,0)", "source": "GKN1", "target": "PIGR"}, {"id": 78, "color": "rgb(0,0,0)", "source": "PIGR", "target": "DDX31"}, {"id": 79, "color": "rgb(0,0,0)", "source": "ARMT1", "target": "HSPB1"}, {"id": 80, "color": "rgb(0,0,0)", "source": "ARMT1", "target": "FGB"}, {"id": 81, "color": "rgb(0,0,0)", "source": "IFT74", "target": "ODF2"}, {"id": 82, "color": "rgb(0,0,0)", "source": "MYO6", "target": "PAK1"}, {"id": 83, "color": "rgb(0,0,0)", "source": "MYO6", "target": "REPS2"}, {"id": 84, "color": "rgb(0,0,0)", "source": "HSPB1", "target": "KRT18"}, {"id": 86, "color": "rgb(0,0,0)", "source": "HSPB1", "target": "PRKCD"}, {"id": 87, "color": "rgb(0,0,0)", "source": "HSPB1", "target": "ASB4"}, {"id": 88, "color": "rgb(0,0,0)", "source": "FOXA1", "target": "NFIX"}, {"id": 89, "color": "rgb(0,0,0)", "source": "ODF2", "target": "MPHOSPH9"}, {"id": 90, "color": "rgb(0,0,0)", "source": "PRKCD", "target": "IRS1"}, {"id": 91, "color": "rgb(0,0,0)", "source": "PRKCD", "target": "IL32"}, {"id": 92, "color": "rgb(0,0,0)", "source": "PAK1", "target": "FGB"}, {"id": 41, "color": "rgb(0,0,0)", "source": "PTPRG", "target": "PSD3"}, {"id": 93, "color": "rgb(0,0,0)", "source": "PTPRG", "target": "SCGB2A2"}, {"id": 94, "color": "rgb(0,0,0)", "source": "TRIM36", "target": "SPICE1"}, {"id": 96, "color": "rgb(0,0,0)", "source": "NIN", "target": "DIAPH3"}, {"id": 99, "color": "rgb(0,0,0)", "source": "ZBTB16", "target": "MX1"}, {"id": 100, "color": "rgb(0,0,0)", "source": "ZBTB16", "target": "IL32"}, {"id": 101, "color": "rgb(0,0,0)", "source": "SPICE1", "target": "DIAPH3"}, {"id": 102, "color": "rgb(0,0,0)", "source": "SPICE1", "target": "MPHOSPH9"}, {"id": 103, "color": "rgb(0,0,0)", "source": "DDX31", "target": "CLU"}, {"id": 40, "color": "rgb(0,0,0)", "source": "MX1", "target": "PSD3"}]}